backgrounder/__init__.py
backgrounder/_compat.py
backgrounder/concurrency.py
backgrounder/decorator.py
backgrounder/py.typed
backgrounder/tasks.py
backgrounder/_internal/__init__.py
backgrounder/_internal/_representation.py
backgrounder-0.2.0.dist-info/METADATA
backgrounder-0.2.0.dist-info/WHEEL
backgrounder-0.2.0.dist-info/licenses/LICENSE
backgrounder-0.2.0.dist-info/RECORD
